{
  "recipes": [
    {"id":1,"name":"Chicken Fried Rice","category":"Dinner","cuisine":"Chinese","difficulty":"Easy","prep_time":"10 min","cook_time":"15 min","servings":4,"dietary_tags":[],"ingredients":[{"name":"chicken breast","qty":"300g"},{"name":"rice","qty":"2 cups"},{"name":"garlic","qty":"4 cloves"},{"name":"soy sauce","qty":"3 tbsp"},{"name":"egg","qty":"2"},{"name":"green onion","qty":"3 stalks"},{"name":"sesame oil","qty":"1 tbsp"},{"name":"carrot","qty":"1"},{"name":"salt","qty":"to taste"}],"instructions":["Cook rice and let it cool completely.","Dice chicken breast into small pieces, season with salt.","Heat oil in a wok over high heat, cook chicken until golden. Set aside.","Scramble eggs in the same wok, set aside.","Add garlic and diced carrot, stir-fry 2 minutes.","Add cold rice, soy sauce, sesame oil. Toss on high heat 3 minutes.","Return chicken and eggs, add green onions. Toss and serve."]},
    {"id":2,"name":"Pasta Aglio e Olio","category":"Dinner","cuisine":"Italian","difficulty":"Easy","prep_time":"5 min","cook_time":"15 min","servings":2,"dietary_tags":["vegetarian"],"ingredients":[{"name":"spaghetti","qty":"200g"},{"name":"garlic","qty":"6 cloves"},{"name":"olive oil","qty":"1/4 cup"},{"name":"red pepper flakes","qty":"1 tsp"},{"name":"parsley","qty":"2 tbsp"},{"name":"parmesan cheese","qty":"2 tbsp"},{"name":"salt","qty":"to taste"}],"instructions":["Boil spaghetti in salted water until al dente. Reserve 1 cup pasta water.","Slice garlic thinly. Heat olive oil on medium-low, cook garlic until golden.","Add red pepper flakes, cook 30 seconds.","Add drained pasta and 1/2 cup pasta water. Toss vigorously.","Add parsley, parmesan, toss. Serve immediately."]},
    {"id":3,"name":"Vegetable Stir Fry","category":"Dinner","cuisine":"Asian","difficulty":"Easy","prep_time":"10 min","cook_time":"10 min","servings":3,"dietary_tags":["vegan","gluten-free"],"ingredients":[{"name":"broccoli","qty":"1 cup"},{"name":"bell pepper","qty":"1"},{"name":"carrot","qty":"1"},{"name":"mushroom","qty":"1 cup"},{"name":"garlic","qty":"3 cloves"},{"name":"ginger","qty":"1 inch"},{"name":"soy sauce","qty":"2 tbsp"},{"name":"cornstarch","qty":"1 tsp"},{"name":"vegetable oil","qty":"2 tbsp"}],"instructions":["Cut all vegetables into bite-sized pieces.","Mix soy sauce, cornstarch and 2 tbsp water for sauce.","Heat oil in wok on high heat. Add garlic and ginger, cook 30 sec.","Add carrots first (2 min), then broccoli and bell pepper (2 min), then mushrooms (1 min).","Pour sauce over, toss 1 minute until glossy. Serve over rice."]},
    {"id":4,"name":"Classic Pancakes","category":"Breakfast","cuisine":"American","difficulty":"Easy","prep_time":"5 min","cook_time":"15 min","servings":4,"dietary_tags":["vegetarian"],"ingredients":[{"name":"flour","qty":"1.5 cups"},{"name":"milk","qty":"1.25 cups"},{"name":"egg","qty":"1"},{"name":"butter","qty":"3 tbsp"},{"name":"sugar","qty":"2 tbsp"},{"name":"baking powder","qty":"2 tsp"},{"name":"salt","qty":"1/4 tsp"},{"name":"vanilla extract","qty":"1 tsp"}],"instructions":["Mix flour, sugar, baking powder, salt in a bowl.","Whisk milk, egg, melted butter, vanilla separately.","Combine wet and dry ingredients. Do not overmix.","Heat a non-stick pan on medium. Pour 1/4 cup batter per pancake.","Cook until bubbles form on surface (2 min), flip, cook 1 more minute.","Serve with maple syrup, berries, or whipped cream."]},
    {"id":5,"name":"Caesar Salad","category":"Lunch","cuisine":"American","difficulty":"Easy","prep_time":"15 min","cook_time":"5 min","servings":2,"dietary_tags":[],"ingredients":[{"name":"romaine lettuce","qty":"1 head"},{"name":"parmesan cheese","qty":"1/2 cup"},{"name":"croutons","qty":"1 cup"},{"name":"chicken breast","qty":"200g"},{"name":"lemon juice","qty":"2 tbsp"},{"name":"garlic","qty":"2 cloves"},{"name":"olive oil","qty":"3 tbsp"},{"name":"egg yolk","qty":"1"},{"name":"salt","qty":"to taste"},{"name":"black pepper","qty":"to taste"}],"instructions":["Grill or pan-sear chicken breast, slice thinly.","For dressing: whisk egg yolk, minced garlic, lemon juice, olive oil, salt, pepper.","Chop romaine lettuce into bite-sized pieces.","Toss lettuce with dressing. Add shaved parmesan and croutons.","Top with sliced chicken. Serve immediately."]},
    {"id":6,"name":"Tomato Soup","category":"Lunch","cuisine":"American","difficulty":"Easy","prep_time":"10 min","cook_time":"25 min","servings":4,"dietary_tags":["vegetarian","gluten-free"],"ingredients":[{"name":"tomato","qty":"6 large"},{"name":"onion","qty":"1"},{"name":"garlic","qty":"4 cloves"},{"name":"olive oil","qty":"2 tbsp"},{"name":"vegetable broth","qty":"2 cups"},{"name":"cream","qty":"1/4 cup"},{"name":"basil","qty":"1/4 cup"},{"name":"salt","qty":"to taste"},{"name":"black pepper","qty":"to taste"},{"name":"sugar","qty":"1 tsp"}],"instructions":["Halve tomatoes, place on baking sheet with olive oil. Roast at 400F for 15 min.","Saute diced onion and garlic in a pot until soft.","Add roasted tomatoes, broth, sugar. Simmer 10 minutes.","Blend until smooth with immersion blender.","Stir in cream and basil. Season with salt and pepper. Serve with bread."]},
    {"id":7,"name":"Egg Omelette","category":"Breakfast","cuisine":"French","difficulty":"Easy","prep_time":"5 min","cook_time":"5 min","servings":1,"dietary_tags":["vegetarian","gluten-free"],"ingredients":[{"name":"egg","qty":"3"},{"name":"butter","qty":"1 tbsp"},{"name":"cheese","qty":"1/4 cup"},{"name":"mushroom","qty":"3"},{"name":"bell pepper","qty":"1/4"},{"name":"onion","qty":"1/4"},{"name":"salt","qty":"to taste"},{"name":"black pepper","qty":"to taste"}],"instructions":["Beat eggs with salt and pepper.","Saute diced mushrooms, bell pepper, onion in butter for 2 minutes.","Pour eggs over vegetables. Cook on medium-low.","When edges set, add cheese. Fold in half.","Cook 30 more seconds. Slide onto plate."]},
    {"id":8,"name":"Butter Chicken","category":"Dinner","cuisine":"Indian","difficulty":"Medium","prep_time":"20 min","cook_time":"30 min","servings":4,"dietary_tags":["gluten-free"],"ingredients":[{"name":"chicken thigh","qty":"500g"},{"name":"yogurt","qty":"1/2 cup"},{"name":"butter","qty":"3 tbsp"},{"name":"onion","qty":"1"},{"name":"garlic","qty":"5 cloves"},{"name":"ginger","qty":"1 inch"},{"name":"tomato puree","qty":"1 cup"},{"name":"cream","qty":"1/2 cup"},{"name":"garam masala","qty":"1 tbsp"},{"name":"turmeric","qty":"1 tsp"},{"name":"chili powder","qty":"1 tsp"},{"name":"salt","qty":"to taste"}],"instructions":["Marinate chicken in yogurt, turmeric, chili powder, salt for 15 min.","Grill or pan-sear marinated chicken until charred. Set aside.","Melt butter, saute onion until golden. Add garlic, ginger paste.","Add tomato puree, garam masala. Simmer 10 minutes.","Add cream, stir. Add cooked chicken pieces.","Simmer 10 more minutes. Garnish with cream and cilantro. Serve with naan or rice."]},
    {"id":9,"name":"Guacamole","category":"Snack","cuisine":"Mexican","difficulty":"Easy","prep_time":"10 min","cook_time":"0 min","servings":4,"dietary_tags":["vegan","gluten-free"],"ingredients":[{"name":"avocado","qty":"3"},{"name":"lime juice","qty":"2 tbsp"},{"name":"onion","qty":"1/4"},{"name":"tomato","qty":"1"},{"name":"cilantro","qty":"2 tbsp"},{"name":"jalapeno","qty":"1"},{"name":"garlic","qty":"1 clove"},{"name":"salt","qty":"to taste"}],"instructions":["Halve avocados, remove pit, scoop into bowl.","Mash with fork to desired consistency.","Add diced onion, tomato, minced jalapeno, garlic, cilantro.","Squeeze lime juice, add salt. Mix gently.","Serve immediately with tortilla chips."]},
    {"id":10,"name":"Banana Smoothie","category":"Breakfast","cuisine":"American","difficulty":"Easy","prep_time":"5 min","cook_time":"0 min","servings":2,"dietary_tags":["vegetarian","gluten-free"],"ingredients":[{"name":"banana","qty":"2"},{"name":"milk","qty":"1 cup"},{"name":"yogurt","qty":"1/2 cup"},{"name":"honey","qty":"1 tbsp"},{"name":"ice","qty":"1 cup"},{"name":"vanilla extract","qty":"1/2 tsp"}],"instructions":["Peel bananas and break into chunks.","Add all ingredients to blender.","Blend on high for 1 minute until smooth.","Pour into glasses and serve immediately."]},
    {"id":11,"name":"Grilled Cheese Sandwich","category":"Lunch","cuisine":"American","difficulty":"Easy","prep_time":"5 min","cook_time":"8 min","servings":1,"dietary_tags":["vegetarian"],"ingredients":[{"name":"bread","qty":"2 slices"},{"name":"cheese","qty":"2 slices"},{"name":"butter","qty":"2 tbsp"}],"instructions":["Butter one side of each bread slice.","Place one slice butter-side down in a skillet over medium heat.","Add cheese slices on top. Place second bread slice butter-side up.","Cook 3-4 minutes until golden brown. Flip carefully.","Cook another 3-4 minutes until cheese melts. Serve hot."]},
    {"id":12,"name":"Chocolate Chip Cookies","category":"Dessert","cuisine":"American","difficulty":"Easy","prep_time":"15 min","cook_time":"12 min","servings":24,"dietary_tags":["vegetarian"],"ingredients":[{"name":"flour","qty":"2.25 cups"},{"name":"butter","qty":"1 cup"},{"name":"sugar","qty":"3/4 cup"},{"name":"brown sugar","qty":"3/4 cup"},{"name":"egg","qty":"2"},{"name":"vanilla extract","qty":"1 tsp"},{"name":"baking soda","qty":"1 tsp"},{"name":"salt","qty":"1 tsp"},{"name":"chocolate chips","qty":"2 cups"}],"instructions":["Preheat oven to 375F (190C).","Cream butter, sugar, and brown sugar until fluffy.","Beat in eggs and vanilla extract.","Mix flour, baking soda, salt. Add to wet mixture gradually.","Fold in chocolate chips.","Drop rounded tablespoons onto baking sheet.","Bake 9-12 minutes until golden edges. Cool on wire rack."]},
    {"id":13,"name":"Dal Tadka","category":"Dinner","cuisine":"Indian","difficulty":"Easy","prep_time":"10 min","cook_time":"25 min","servings":4,"dietary_tags":["vegan","gluten-free"],"ingredients":[{"name":"yellow lentils","qty":"1 cup"},{"name":"onion","qty":"1"},{"name":"tomato","qty":"2"},{"name":"garlic","qty":"4 cloves"},{"name":"ginger","qty":"1 inch"},{"name":"turmeric","qty":"1/2 tsp"},{"name":"cumin seeds","qty":"1 tsp"},{"name":"red chili","qty":"2"},{"name":"ghee","qty":"2 tbsp"},{"name":"cilantro","qty":"2 tbsp"},{"name":"salt","qty":"to taste"}],"instructions":["Wash lentils. Pressure cook with turmeric, salt and 3 cups water for 3 whistles.","For tadka: heat ghee, add cumin seeds, dried red chili.","Add chopped onion, cook until golden. Add garlic and ginger.","Add chopped tomatoes, cook until soft.","Pour tadka over cooked dal. Mix well.","Garnish with cilantro. Serve with rice or roti."]},
    {"id":14,"name":"Fish Tacos","category":"Dinner","cuisine":"Mexican","difficulty":"Medium","prep_time":"15 min","cook_time":"10 min","servings":4,"dietary_tags":[],"ingredients":[{"name":"white fish fillet","qty":"400g"},{"name":"tortilla","qty":"8"},{"name":"cabbage","qty":"2 cups"},{"name":"lime juice","qty":"3 tbsp"},{"name":"sour cream","qty":"1/4 cup"},{"name":"chili powder","qty":"1 tsp"},{"name":"cumin","qty":"1/2 tsp"},{"name":"garlic powder","qty":"1/2 tsp"},{"name":"olive oil","qty":"2 tbsp"},{"name":"cilantro","qty":"2 tbsp"},{"name":"salt","qty":"to taste"}],"instructions":["Season fish with chili powder, cumin, garlic powder, salt.","Heat olive oil in skillet. Cook fish 3-4 min per side until flaky.","Shred cabbage, toss with lime juice.","Mix sour cream with a squeeze of lime for sauce.","Warm tortillas in a dry pan.","Assemble: tortilla, cabbage slaw, flaked fish, cream sauce, cilantro."]},
    {"id":15,"name":"French Toast","category":"Breakfast","cuisine":"French","difficulty":"Easy","prep_time":"5 min","cook_time":"10 min","servings":2,"dietary_tags":["vegetarian"],"ingredients":[{"name":"bread","qty":"4 slices"},{"name":"egg","qty":"2"},{"name":"milk","qty":"1/2 cup"},{"name":"cinnamon","qty":"1 tsp"},{"name":"vanilla extract","qty":"1 tsp"},{"name":"butter","qty":"2 tbsp"},{"name":"sugar","qty":"1 tbsp"},{"name":"maple syrup","qty":"to serve"}],"instructions":["Whisk eggs, milk, cinnamon, vanilla, sugar in a bowl.","Heat butter in a skillet over medium heat.","Dip each bread slice in egg mixture, coating both sides.","Cook 2-3 minutes per side until golden brown.","Serve with maple syrup and fresh berries."]},
    {"id":16,"name":"Mushroom Risotto","category":"Dinner","cuisine":"Italian","difficulty":"Medium","prep_time":"10 min","cook_time":"30 min","servings":3,"dietary_tags":["vegetarian","gluten-free"],"ingredients":[{"name":"arborio rice","qty":"1.5 cups"},{"name":"mushroom","qty":"2 cups"},{"name":"onion","qty":"1"},{"name":"garlic","qty":"3 cloves"},{"name":"vegetable broth","qty":"4 cups"},{"name":"white wine","qty":"1/2 cup"},{"name":"parmesan cheese","qty":"1/2 cup"},{"name":"butter","qty":"2 tbsp"},{"name":"olive oil","qty":"1 tbsp"},{"name":"salt","qty":"to taste"},{"name":"black pepper","qty":"to taste"}],"instructions":["Keep broth warm in a separate pot.","Saute mushrooms in olive oil until golden. Set aside.","Cook diced onion and garlic in butter until soft.","Toast rice for 2 minutes, stirring constantly.","Add wine, stir until absorbed.","Add broth one ladle at a time, stirring constantly for 18 minutes.","Fold in mushrooms, parmesan, and butter. Season and serve."]},
    {"id":17,"name":"Hummus","category":"Snack","cuisine":"Middle Eastern","difficulty":"Easy","prep_time":"10 min","cook_time":"0 min","servings":6,"dietary_tags":["vegan","gluten-free"],"ingredients":[{"name":"chickpeas","qty":"1 can"},{"name":"tahini","qty":"3 tbsp"},{"name":"lemon juice","qty":"3 tbsp"},{"name":"garlic","qty":"2 cloves"},{"name":"olive oil","qty":"3 tbsp"},{"name":"cumin","qty":"1/2 tsp"},{"name":"salt","qty":"to taste"},{"name":"paprika","qty":"for garnish"}],"instructions":["Drain and rinse chickpeas.","Blend chickpeas, tahini, lemon juice, garlic, cumin, salt in food processor.","Drizzle in olive oil while blending until smooth.","Add 2-3 tbsp ice water for creamier texture.","Transfer to bowl, garnish with paprika, olive oil. Serve with pita."]},
    {"id":18,"name":"Chicken Biryani","category":"Dinner","cuisine":"Indian","difficulty":"Hard","prep_time":"30 min","cook_time":"45 min","servings":6,"dietary_tags":["gluten-free"],"ingredients":[{"name":"basmati rice","qty":"2 cups"},{"name":"chicken thigh","qty":"500g"},{"name":"yogurt","qty":"1 cup"},{"name":"onion","qty":"2"},{"name":"garlic","qty":"6 cloves"},{"name":"ginger","qty":"2 inch"},{"name":"tomato","qty":"2"},{"name":"garam masala","qty":"1 tbsp"},{"name":"turmeric","qty":"1 tsp"},{"name":"chili powder","qty":"1 tsp"},{"name":"saffron","qty":"pinch"},{"name":"mint","qty":"1/4 cup"},{"name":"cilantro","qty":"1/4 cup"},{"name":"ghee","qty":"3 tbsp"},{"name":"salt","qty":"to taste"}],"instructions":["Soak rice 30 min. Parboil until 70% cooked, drain.","Marinate chicken in yogurt, garam masala, turmeric, chili, salt.","Fry sliced onions in ghee until deep golden. Set half aside.","Add garlic-ginger paste, cook 2 min. Add tomatoes.","Add marinated chicken, cook 10 min until half done.","Layer: chicken at bottom, rice on top, fried onions, mint, saffron milk.","Seal pot, cook on low heat 25 min. Rest 5 min, then gently mix and serve."]},
    {"id":19,"name":"Caprese Salad","category":"Lunch","cuisine":"Italian","difficulty":"Easy","prep_time":"10 min","cook_time":"0 min","servings":2,"dietary_tags":["vegetarian","gluten-free"],"ingredients":[{"name":"mozzarella","qty":"200g"},{"name":"tomato","qty":"3 large"},{"name":"basil","qty":"10 leaves"},{"name":"olive oil","qty":"2 tbsp"},{"name":"balsamic vinegar","qty":"1 tbsp"},{"name":"salt","qty":"to taste"},{"name":"black pepper","qty":"to taste"}],"instructions":["Slice mozzarella and tomatoes into 1/4 inch rounds.","Arrange alternating slices of tomato and mozzarella on plate.","Tuck fresh basil leaves between slices.","Drizzle with olive oil and balsamic vinegar.","Season with salt and pepper. Serve immediately."]},
    {"id":20,"name":"Mango Lassi","category":"Breakfast","cuisine":"Indian","difficulty":"Easy","prep_time":"5 min","cook_time":"0 min","servings":2,"dietary_tags":["vegetarian","gluten-free"],"ingredients":[{"name":"mango","qty":"1 large"},{"name":"yogurt","qty":"1 cup"},{"name":"milk","qty":"1/2 cup"},{"name":"sugar","qty":"2 tbsp"},{"name":"cardamom","qty":"1/4 tsp"},{"name":"ice","qty":"1 cup"}],"instructions":["Peel and dice mango.","Add mango, yogurt, milk, sugar, cardamom, ice to blender.","Blend until smooth and frothy.","Pour into glasses. Garnish with a pinch of cardamom."]},
    {"id":21,"name":"Beef Tacos","category":"Dinner","cuisine":"Mexican","difficulty":"Easy","prep_time":"10 min","cook_time":"15 min","servings":4,"dietary_tags":[],"ingredients":[{"name":"ground beef","qty":"500g"},{"name":"tortilla","qty":"8"},{"name":"onion","qty":"1"},{"name":"garlic","qty":"3 cloves"},{"name":"chili powder","qty":"2 tsp"},{"name":"cumin","qty":"1 tsp"},{"name":"tomato","qty":"2"},{"name":"lettuce","qty":"1 cup"},{"name":"cheese","qty":"1/2 cup"},{"name":"sour cream","qty":"1/4 cup"},{"name":"salt","qty":"to taste"}],"instructions":["Cook ground beef in skillet, breaking into crumbles.","Add diced onion and garlic, cook 3 minutes.","Add chili powder, cumin, salt. Stir well.","Add diced tomatoes, simmer 5 minutes.","Warm tortillas in a dry pan.","Assemble: tortilla, beef, lettuce, cheese, sour cream."]},
    {"id":22,"name":"Tiramisu","category":"Dessert","cuisine":"Italian","difficulty":"Medium","prep_time":"30 min","cook_time":"0 min","servings":6,"dietary_tags":["vegetarian"],"ingredients":[{"name":"mascarpone","qty":"500g"},{"name":"egg","qty":"4"},{"name":"sugar","qty":"1/2 cup"},{"name":"espresso","qty":"1 cup"},{"name":"ladyfinger biscuits","qty":"24"},{"name":"cocoa powder","qty":"2 tbsp"},{"name":"vanilla extract","qty":"1 tsp"}],"instructions":["Brew espresso and let it cool.","Separate eggs. Beat yolks with sugar until pale and thick.","Fold in mascarpone and vanilla until smooth.","Beat egg whites until stiff peaks. Fold into mascarpone mixture.","Dip ladyfingers briefly in espresso. Layer in dish.","Spread mascarpone mixture over ladyfingers. Repeat layers.","Dust with cocoa powder. Refrigerate 4 hours minimum. Serve cold."]},
    {"id":23,"name":"Greek Salad","category":"Lunch","cuisine":"Mediterranean","difficulty":"Easy","prep_time":"10 min","cook_time":"0 min","servings":2,"dietary_tags":["vegetarian","gluten-free"],"ingredients":[{"name":"cucumber","qty":"1"},{"name":"tomato","qty":"2"},{"name":"red onion","qty":"1/2"},{"name":"feta cheese","qty":"100g"},{"name":"olives","qty":"1/2 cup"},{"name":"olive oil","qty":"3 tbsp"},{"name":"lemon juice","qty":"1 tbsp"},{"name":"oregano","qty":"1 tsp"},{"name":"salt","qty":"to taste"}],"instructions":["Dice cucumber, tomatoes, and red onion into chunks.","Add to bowl with olives.","Crumble feta cheese on top.","Whisk olive oil, lemon juice, oregano, salt for dressing.","Drizzle dressing over salad. Toss gently and serve."]},
    {"id":24,"name":"Chicken Quesadilla","category":"Lunch","cuisine":"Mexican","difficulty":"Easy","prep_time":"10 min","cook_time":"10 min","servings":2,"dietary_tags":[],"ingredients":[{"name":"chicken breast","qty":"200g"},{"name":"tortilla","qty":"4"},{"name":"cheese","qty":"1 cup"},{"name":"bell pepper","qty":"1"},{"name":"onion","qty":"1/2"},{"name":"cumin","qty":"1/2 tsp"},{"name":"chili powder","qty":"1/2 tsp"},{"name":"olive oil","qty":"1 tbsp"},{"name":"sour cream","qty":"to serve"},{"name":"salt","qty":"to taste"}],"instructions":["Cook diced chicken with cumin, chili powder, salt until done.","Saute diced bell pepper and onion until soft.","Place tortilla in skillet. Add cheese, chicken, peppers, onion on one half.","Fold tortilla in half. Cook 2-3 min per side until golden and cheese melts.","Cut into wedges. Serve with sour cream and salsa."]},
    {"id":25,"name":"Banana Bread","category":"Dessert","cuisine":"American","difficulty":"Easy","prep_time":"15 min","cook_time":"60 min","servings":8,"dietary_tags":["vegetarian"],"ingredients":[{"name":"banana","qty":"3 ripe"},{"name":"flour","qty":"1.5 cups"},{"name":"sugar","qty":"3/4 cup"},{"name":"butter","qty":"1/3 cup"},{"name":"egg","qty":"1"},{"name":"baking soda","qty":"1 tsp"},{"name":"salt","qty":"pinch"},{"name":"vanilla extract","qty":"1 tsp"},{"name":"cinnamon","qty":"1/2 tsp"}],"instructions":["Preheat oven to 350F (175C). Grease a loaf pan.","Mash bananas in a large bowl.","Mix in melted butter, sugar, egg, vanilla.","Add flour, baking soda, salt, cinnamon. Stir until just combined.","Pour into loaf pan.","Bake 55-60 minutes until toothpick comes out clean.","Cool 10 minutes in pan, then transfer to wire rack."]}
  ]
}
